exifstrip/__init__.py
exifstrip/main.py
exifstrip-0.0.3.dist-info/METADATA
exifstrip-0.0.3.dist-info/WHEEL
exifstrip-0.0.3.dist-info/entry_points.txt
exifstrip-0.0.3.dist-info/top_level.txt
exifstrip-0.0.3.dist-info/RECORD
