Metadata-Version: 2.1
Name: exifstrip
Version: 0.0.3
Summary: Remove EXIF data from images.
Home-page: https://github.com/bradendubois/exif-strip
Author: Braden Dubois
Author-email: braden.dubois@usask.ca
License: UNKNOWN
Keywords: exif image python
Platform: UNKNOWN
Requires-Dist: pillow
Requires-Dist: pillow-heif
